checkend/__init__.py
checkend/client.py
checkend/configuration.py
checkend/notice.py
checkend/notice_builder.py
checkend/testing.py
checkend/version.py
checkend/worker.py
checkend/filters/__init__.py
checkend/filters/ignore_filter.py
checkend/filters/sanitize_filter.py
checkend/integrations/__init__.py
checkend/integrations/celery.py
checkend/integrations/django.py
checkend/integrations/dramatiq.py
checkend/integrations/fastapi.py
checkend/integrations/flask.py
checkend/integrations/rq.py
checkend-1.0.0.dist-info/licenses/LICENSE
checkend-1.0.0.dist-info/METADATA
checkend-1.0.0.dist-info/WHEEL
checkend-1.0.0.dist-info/top_level.txt
checkend-1.0.0.dist-info/RECORD
