Metadata-Version: 2.4
Name: checkend
Version: 1.0.0
Summary: Python SDK for Checkend error monitoring
Author-email: Furvur <hello@furvur.com>
License: MIT
Project-URL: Homepage, https://checkend.com
Project-URL: Documentation, https://checkend.com/docs
Project-URL: Repository, https://github.com/furvur/checkend-python
Project-URL: Issues, https://github.com/furvur/checkend-python/issues
Keywords: error-monitoring,exception-tracking,checkend,debugging
Classifier: Development Status :: 4 - Beta
Classifier: Intended Audience :: Developers
Classifier: License :: OSI Approved :: MIT License
Classifier: Operating System :: OS Independent
Classifier: Programming Language :: Python :: 3
Classifier: Programming Language :: Python :: 3.9
Classifier: Programming Language :: Python :: 3.10
Classifier: Programming Language :: Python :: 3.11
Classifier: Programming Language :: Python :: 3.12
Classifier: Programming Language :: Python :: 3.13
Classifier: Topic :: Software Development :: Bug Tracking
Classifier: Topic :: System :: Monitoring
Requires-Python: >=3.9
License-File: LICENSE
Provides-Extra: dev
Requires-Dist: pytest>=7.0; extra == "dev"
Requires-Dist: pytest-cov>=4.0; extra == "dev"
Requires-Dist: responses>=0.23; extra == "dev"
Requires-Dist: ruff>=0.1; extra == "dev"
Dynamic: license-file
